alfahor/__init__.py
alfahor/alfahor.py
alfahor-1.1.0.dist-info/LICENSE
alfahor-1.1.0.dist-info/METADATA
alfahor-1.1.0.dist-info/WHEEL
alfahor-1.1.0.dist-info/top_level.txt
alfahor-1.1.0.dist-info/RECORD
