Metadata-Version: 2.1
Name: alfahor
Version: 1.1.0
Summary: Vertical structure from masked channel maps.
Home-page: https://github.com/teresapaz/alfahor
Author: Teresa Paneque-Carreño
Author-email: tpaneque@umich.edu
License: LICENSE.md
License-File: LICENSE
Requires-Dist: numpy
Requires-Dist: scipy
Requires-Dist: opencv-python
Requires-Dist: matplotlib
Requires-Dist: astropy
